string_gen/__init__.py
string_gen/__version__.py
string_gen/generator.py
string_gen-0.1.1.dist-info/licenses/LICENSE
string_gen-0.1.1.dist-info/METADATA
string_gen-0.1.1.dist-info/WHEEL
string_gen-0.1.1.dist-info/top_level.txt
string_gen-0.1.1.dist-info/RECORD
